{"status": 0, "amq": {"date": null, "status": 0, "resp": null, "req": [[], [{"Honoraires": "82 $", "Code": "1120", "Description": "EXAMEN COMPLET, DENTITION MIXTE", "Frais": "0 $", "codeRole": "1", "ramq_id": 1, "Surface": "", "Dent": "", "Prod": "", "row_id": "1", "Total": "82.00 $", "Type": "AMQ", "undefined": "PlusSupprimer"}], [[{"name": "row_id", "value": "1"}, {"name": "no_autor_proth_acryl_denti", "value": ""}, {"name": "dat_autor_proth_acryl_denti", "value": ""}, {"name": "typ_id_rais_trait_denta_denti", "value": ""}, {"name": "id_rais_trait_denta_denti", "value": ""}, {"name": "typ_id_site_trait_denta_denti", "value": ""}, {"name": "id_site_trait_denta_denti", "value": ""}, {"name": "dat_serv_elm_fact_denti", "value": "2017-07-04"}, {"name": "date_debu_lev", "value": ""}, {"name": "time_debu_lev", "value": ""}, {"name": "typ_refre_lieu_denti", "value": ""}, {"name": "id_lieu_phys_denti", "value": ""}, {"name": "no_sect_activ_refr_denti", "value": ""}, {"name": "code_postal_geo_denti", "value": ""}, {"name": "code_localite_geo_denti", "value": ""}, {"name": "no_bureau_geo_denti", "value": ""}, {"name": "id_prof_refre_denti", "value": ""}, {"name": "typ_refre_autre_prof_denti", "value": "1"}, {"name": "date_lappel_lev", "value": ""}, {"name": "time_lappel", "value": ""}]]], "nofact": "158"}, "cas": {"date": null, "status": 0, "resp": null, "req": [], "nofact": "158"}, "ins": {"date": null, "status": 0, "resp": null, "req": [], "nofact": "158"}}