{"id":"3882","date":"2016-08-09","exist":[{"code":"23121","tooth":25,"surface":"","note":""},{"code":"23210","tooth":25,"surface":"","note":""},{"code":"23220","tooth":25,"surface":"","note":""},{"code":"23221","tooth":33,"surface":"LBDO","note":""},{"code":"23210","tooth":42,"surface":"M","note":""},{"code":"23213","tooth":42,"surface":"M","note":""},{"code":"23224","tooth":42,"surface":"M","note":""}],"todo":[{"code":"72230","tooth":18,"surface":"","note":""},{"code":"72230","tooth":28,"surface":"","note":""},{"code":"72230","tooth":48,"surface":"","note":""},{"code":"72230","tooth":38,"surface":"","note":""}],"observ":[],"signFile0":"S_3882_1470759039412","date0":"2016/08/09","signFile1":"S_3333","date1":"2016/08/09"}